<?xml version="1.0" standalone="yes"?>
<dsSingerHistory xmlns="http://tempuri.org/dsSingerHistory.xsd">
  <dtSingerHistory>
    <Count>1</Count>
    <DateTimeSang>2009-12-21T01:55:26.2442907-08:00</DateTimeSang>
    <Title>I'm So Excited</Title>
    <Artist>Pointer Sisters, The</Artist>
    <DiscID />
    <Pitch>0</Pitch>
    <Path>C:\Users\Karaoke\Music\karaoke\CHB\Pointer Sisters, The - I'm So Excited.zip</Path>
    <Tempo>0</Tempo>
    <StartPoint>0</StartPoint>
    <EndPoint>0</EndPoint>
  </dtSingerHistory>
  <dtSingerHistory>
    <Count>1</Count>
    <DateTimeSang>2010-06-07T01:35:00.2414972-07:00</DateTimeSang>
    <Title>Ain't No Mountain High Enough</Title>
    <Artist>Ross, Diana</Artist>
    <DiscID />
    <Pitch>0</Pitch>
    <Path>C:\Users\Karaoke\Music\karaoke\CHB\Ross, Diana - Ain't No Mountain High Enough.zip</Path>
    <Tempo>0</Tempo>
    <StartPoint>0</StartPoint>
    <EndPoint>0</EndPoint>
  </dtSingerHistory>
  <dtSingerHistory>
    <Count>1</Count>
    <DateTimeSang>2010-06-21T01:29:32.4007254-07:00</DateTimeSang>
    <Title>Twist And Shout</Title>
    <Artist>Beatles, The</Artist>
    <DiscID />
    <Pitch>0</Pitch>
    <Path>C:\Users\Karaoke\Music\karaoke\Dec-SC\dec sc\december sc convert final-5\Beatles, The - Twist And Shout.zip</Path>
    <Tempo>0</Tempo>
    <StartPoint>0</StartPoint>
    <EndPoint>0</EndPoint>
  </dtSingerHistory>
  <dtSingerHistory>
    <Count>1</Count>
    <DateTimeSang>2010-07-12T01:31:53.8974344-07:00</DateTimeSang>
    <Title>Last Dance</Title>
    <Artist>Summer, Donna</Artist>
    <DiscID />
    <Pitch>0</Pitch>
    <Path>C:\Users\Karaoke\Music\karaoke\SC Foundations\Summer, Donna - Last Dance.zip</Path>
    <Tempo>0</Tempo>
    <StartPoint>0</StartPoint>
    <EndPoint>0</EndPoint>
  </dtSingerHistory>
  <dtSingerHistory>
    <Count>1</Count>
    <DateTimeSang>2013-03-17T21:40:12.3996388-07:00</DateTimeSang>
    <Title>Wannabe</Title>
    <Artist>Spice Girls</Artist>
    <DiscID />
    <Pitch>0</Pitch>
    <Path>C:\Users\Karaoke\Music\karaoke\CHB\Spice Girls - Wannabe.zip</Path>
    <Tempo>0</Tempo>
    <StartPoint>0</StartPoint>
    <EndPoint>0</EndPoint>
  </dtSingerHistory>
</dsSingerHistory>