<?xml version="1.0" standalone="yes"?>
<dsSingerHistory xmlns="http://tempuri.org/dsSingerHistory.xsd">
  <dtSingerHistory>
    <Count>1</Count>
    <DateTimeSang>2010-01-01T00:15:48.9730947-08:00</DateTimeSang>
    <Title>Poker Face</Title>
    <Artist>Lady Gaga</Artist>
    <DiscID />
    <Pitch>0</Pitch>
    <Path>C:\Users\Karaoke\Music\karaoke\2009 June\Lady Gaga - Poker Face.zip</Path>
    <Tempo>0</Tempo>
    <StartPoint>0</StartPoint>
    <EndPoint>0</EndPoint>
  </dtSingerHistory>
  <dtSingerHistory>
    <Count>1</Count>
    <DateTimeSang>2010-01-01T01:03:12.2417204-08:00</DateTimeSang>
    <Title>Paparazzi</Title>
    <Artist>Lady Gaga</Artist>
    <DiscID />
    <Pitch>0</Pitch>
    <Path>C:\Users\Karaoke\Music\karaoke\2009 June\Lady Gaga - Paparazzi.zip</Path>
    <Tempo>0</Tempo>
    <StartPoint>0</StartPoint>
    <EndPoint>0</EndPoint>
  </dtSingerHistory>
  <dtSingerHistory>
    <Count>1</Count>
    <DateTimeSang>2010-01-01T01:27:45.9130096-08:00</DateTimeSang>
    <Title>Whenever, Whatever</Title>
    <Artist>Shakira</Artist>
    <DiscID />
    <Pitch>0</Pitch>
    <Path>C:\Users\Karaoke\Music\karaoke\random crap\Shakira - Whenever, Whatever.zip</Path>
    <Tempo>0</Tempo>
    <StartPoint>0</StartPoint>
    <EndPoint>0</EndPoint>
  </dtSingerHistory>
  <dtSingerHistory>
    <Count>1</Count>
    <DateTimeSang>2010-01-23T22:50:49.8629779-08:00</DateTimeSang>
    <Title>I Will Survive</Title>
    <Artist>Gaynor, Gloria</Artist>
    <DiscID />
    <Pitch>0</Pitch>
    <Path>C:\Users\Karaoke\Music\karaoke\sgb\Gaynor, Gloria - I Will Survive.zip</Path>
    <Tempo>0</Tempo>
    <StartPoint>0</StartPoint>
    <EndPoint>0</EndPoint>
  </dtSingerHistory>
  <dtSingerHistory>
    <Count>1</Count>
    <DateTimeSang>2010-05-01T23:01:51.3237173-07:00</DateTimeSang>
    <Title>Top Of The World</Title>
    <Artist>Carpenters, The</Artist>
    <DiscID />
    <Pitch>0</Pitch>
    <Path>C:\Users\Karaoke\Music\karaoke\CHB\Carpenters, The - Top Of The World.zip</Path>
    <Tempo>0</Tempo>
    <StartPoint>0</StartPoint>
    <EndPoint>0</EndPoint>
  </dtSingerHistory>
  <dtSingerHistory>
    <Count>1</Count>
    <DateTimeSang>2010-05-01T23:38:16.7977192-07:00</DateTimeSang>
    <Title>Poker Face</Title>
    <Artist>Lady GaGa</Artist>
    <DiscID />
    <Pitch>0</Pitch>
    <Path>C:\Users\Karaoke\Music\karaoke\LABELED 3\ZOOM DL\Lady GaGa - Poker Face.zip</Path>
    <Tempo>0</Tempo>
    <StartPoint>0</StartPoint>
    <EndPoint>0</EndPoint>
  </dtSingerHistory>
  <dtSingerHistory>
    <Count>2</Count>
    <DateTimeSang>2010-08-22T21:51:14.2720278-07:00</DateTimeSang>
    <Title>Black Velvet</Title>
    <Artist>Myles, Alannah</Artist>
    <DiscID />
    <Pitch>0</Pitch>
    <Path>C:\Users\Karaoke\Music\karaoke\SC Foundations\Myles, Alannah - Black Velvet.zip</Path>
    <Tempo>0</Tempo>
    <StartPoint>0</StartPoint>
    <EndPoint>0</EndPoint>
  </dtSingerHistory>
  <dtSingerHistory>
    <Count>1</Count>
    <DateTimeSang>2011-04-30T23:23:07.9740059-07:00</DateTimeSang>
    <Title>What's Up</Title>
    <Artist>Four Non Blondes</Artist>
    <DiscID />
    <Pitch>0</Pitch>
    <Path>C:\Users\Karaoke\Music\karaoke\Supercore 2006\Four Non Blondes - What's Up.zip</Path>
    <Tempo>0</Tempo>
    <StartPoint>0</StartPoint>
    <EndPoint>0</EndPoint>
  </dtSingerHistory>
  <dtSingerHistory>
    <Count>1</Count>
    <DateTimeSang>2011-05-01T00:07:56.7747965-07:00</DateTimeSang>
    <Title>Open Your Heart</Title>
    <Artist>Madonna</Artist>
    <DiscID />
    <Pitch>0</Pitch>
    <Path>C:\Users\Karaoke\Music\karaoke\LABELED 3\SBI\Madonna - Open Your Heart.zip</Path>
    <Tempo>0</Tempo>
    <StartPoint>0</StartPoint>
    <EndPoint>0</EndPoint>
  </dtSingerHistory>
  <dtSingerHistory>
    <Count>1</Count>
    <DateTimeSang>2011-07-31T21:30:29.8533899-07:00</DateTimeSang>
    <Title>Them Bones</Title>
    <Artist>Alice In Chains</Artist>
    <DiscID />
    <Pitch>0</Pitch>
    <Path>C:\Users\Karaoke\Music\karaoke\LABELED 2\SBI\Alice In Chains - Them Bones.zip</Path>
    <Tempo>0</Tempo>
    <StartPoint>0</StartPoint>
    <EndPoint>0</EndPoint>
  </dtSingerHistory>
  <dtSingerHistory>
    <Count>1</Count>
    <DateTimeSang>2011-07-31T22:32:56.2446712-07:00</DateTimeSang>
    <Title>Babooshka</Title>
    <Artist>Bush, Kate</Artist>
    <DiscID />
    <Pitch>0</Pitch>
    <Path>C:\Users\Karaoke\Music\karaoke\SUN\Bush, Kate - Babooshka.zip</Path>
    <Tempo>0</Tempo>
    <StartPoint>0</StartPoint>
    <EndPoint>0</EndPoint>
  </dtSingerHistory>
  <dtSingerHistory>
    <Count>1</Count>
    <DateTimeSang>2011-08-03T21:44:44.2608447-07:00</DateTimeSang>
    <Title>Wow</Title>
    <Artist>Bush, Kate</Artist>
    <DiscID />
    <Pitch>0</Pitch>
    <Path>C:\Users\Karaoke\Music\karaoke\2011 April\04-10\Bush, Kate - Wow.zip</Path>
    <Tempo>0</Tempo>
    <StartPoint>0</StartPoint>
    <EndPoint>0</EndPoint>
  </dtSingerHistory>
  <dtSingerHistory>
    <Count>1</Count>
    <DateTimeSang>2011-08-03T22:21:04.8865694-07:00</DateTimeSang>
    <Title>Army Dreamers</Title>
    <Artist>Bush, Kate</Artist>
    <DiscID />
    <Pitch>0</Pitch>
    <Path>C:\Users\Karaoke\Music\karaoke\LABELED 3\SUN\Bush, Kate - Army Dreamers.zip</Path>
    <Tempo>0</Tempo>
    <StartPoint>0</StartPoint>
    <EndPoint>0</EndPoint>
  </dtSingerHistory>
  <dtSingerHistory>
    <Count>1</Count>
    <DateTimeSang>2011-08-03T22:47:42.5079481-07:00</DateTimeSang>
    <Title>Cloudbusting</Title>
    <Artist>Bush, Kate</Artist>
    <DiscID />
    <Pitch>0</Pitch>
    <Path>C:\Users\Karaoke\Music\karaoke\LABELED 3\SUN DL\Bush, Kate - Cloudbusting.zip</Path>
    <Tempo>0</Tempo>
    <StartPoint>0</StartPoint>
    <EndPoint>0</EndPoint>
  </dtSingerHistory>
  <dtSingerHistory>
    <Count>1</Count>
    <DateTimeSang>2011-08-03T23:35:54.874382-07:00</DateTimeSang>
    <Title>Peek-A-Boo</Title>
    <Artist>Siouxsie &amp; The Banshees</Artist>
    <DiscID />
    <Pitch>0</Pitch>
    <Path>C:\Users\Karaoke\Music\karaoke\LABELED 3\SUN DL\Siouxsie &amp; The Banshees - Peek-A-Boo.zip</Path>
    <Tempo>0</Tempo>
    <StartPoint>0</StartPoint>
    <EndPoint>0</EndPoint>
  </dtSingerHistory>
  <dtSingerHistory>
    <Count>1</Count>
    <DateTimeSang>2011-09-04T23:04:18.0157996-07:00</DateTimeSang>
    <Title>Volcano Girls</Title>
    <Artist>Veruca Salt</Artist>
    <DiscID />
    <Pitch>0</Pitch>
    <Path>C:\Users\Karaoke\Music\karaoke\SC new adds\Veruca Salt - Volcano Girls.zip</Path>
    <Tempo>0</Tempo>
    <StartPoint>0</StartPoint>
    <EndPoint>0</EndPoint>
  </dtSingerHistory>
  <dtSingerHistory>
    <Count>1</Count>
    <DateTimeSang>2012-04-05T22:10:26.2335669-07:00</DateTimeSang>
    <Title>Bring On The Dancing Horses</Title>
    <Artist>Echo &amp; The Bunnymen</Artist>
    <DiscID />
    <Pitch>0</Pitch>
    <Path>C:\Users\Karaoke\Music\karaoke\2011\2011 April\04-09\Echo &amp; The Bunnymen - Bring On The Dancing Horses.zip</Path>
    <Tempo>0</Tempo>
    <StartPoint>0</StartPoint>
    <EndPoint>0</EndPoint>
  </dtSingerHistory>
  <dtSingerHistory>
    <Count>1</Count>
    <DateTimeSang>2012-04-05T23:23:42.955045-07:00</DateTimeSang>
    <Title>All My Friends</Title>
    <Artist>LCD Soundsystem</Artist>
    <DiscID />
    <Pitch>0</Pitch>
    <Path>C:\Users\Karaoke\Music\karaoke\2011\2011 December\12-18\LCD Soundsystem - All My Friends.zip</Path>
    <Tempo>0</Tempo>
    <StartPoint>0</StartPoint>
    <EndPoint>0</EndPoint>
  </dtSingerHistory>
  <dtSingerHistory>
    <Count>1</Count>
    <DateTimeSang>2012-04-13T22:13:43.990038-07:00</DateTimeSang>
    <Title>Kids In America</Title>
    <Artist>Wilde, Kim</Artist>
    <DiscID />
    <Pitch>0</Pitch>
    <Path>C:\Users\Karaoke\Music\karaoke\Dec-SC\dec sc\december sc convert final-2\Wilde, Kim - Kids In America.zip</Path>
    <Tempo>0</Tempo>
    <StartPoint>0</StartPoint>
    <EndPoint>0</EndPoint>
  </dtSingerHistory>
  <dtSingerHistory>
    <Count>1</Count>
    <DateTimeSang>2012-04-13T23:19:03.5802258-07:00</DateTimeSang>
    <Title>No More Words</Title>
    <Artist>Berlin</Artist>
    <DiscID />
    <Pitch>0</Pitch>
    <Path>C:\Users\Karaoke\Music\karaoke\LABELED 3\SC\Berlin - No More Words.zip</Path>
    <Tempo>0</Tempo>
    <StartPoint>0</StartPoint>
    <EndPoint>0</EndPoint>
  </dtSingerHistory>
  <dtSingerHistory>
    <Count>1</Count>
    <DateTimeSang>2012-04-29T00:07:16.0140598-07:00</DateTimeSang>
    <Title>Bad Romance</Title>
    <Artist>Lady Gaga</Artist>
    <DiscID />
    <Pitch>0</Pitch>
    <Path>C:\Users\Karaoke\Music\karaoke\LABELED 3\ZOOM DL\Lady Gaga - Bad Romance.zip</Path>
    <Tempo>0</Tempo>
    <StartPoint>0</StartPoint>
    <EndPoint>0</EndPoint>
  </dtSingerHistory>
  <dtSingerHistory>
    <Count>1</Count>
    <DateTimeSang>2012-05-04T22:56:16.1439209-07:00</DateTimeSang>
    <Title>Hanging On The Telephone</Title>
    <Artist>Blondie</Artist>
    <DiscID />
    <Pitch>0</Pitch>
    <Path>C:\Users\Karaoke\Music\karaoke\LABELED 3\SUN\Blondie - Hanging On The Telephone.zip</Path>
    <Tempo>0</Tempo>
    <StartPoint>0</StartPoint>
    <EndPoint>0</EndPoint>
  </dtSingerHistory>
  <dtSingerHistory>
    <Count>1</Count>
    <DateTimeSang>2012-05-05T00:15:15.1089742-07:00</DateTimeSang>
    <Title>She's Crafty</Title>
    <Artist>Beastie Boys</Artist>
    <DiscID />
    <Pitch>0</Pitch>
    <Path>C:\Users\Karaoke\Music\karaoke\2011\2011 January\1-01\Beastie Boys - She's Crafty.zip</Path>
    <Tempo>0</Tempo>
    <StartPoint>0</StartPoint>
    <EndPoint>0</EndPoint>
  </dtSingerHistory>
  <dtSingerHistory>
    <Count>1</Count>
    <DateTimeSang>2012-06-07T22:52:21.8889775-07:00</DateTimeSang>
    <Title>Wishing</Title>
    <Artist>Flock Of Seagulls</Artist>
    <DiscID />
    <Pitch>0</Pitch>
    <Path>C:\Users\Karaoke\Music\karaoke\2010 July\07-01\Flock Of Seagulls - Wishing.zip</Path>
    <Tempo>0</Tempo>
    <StartPoint>0</StartPoint>
    <EndPoint>0</EndPoint>
  </dtSingerHistory>
  <dtSingerHistory>
    <Count>1</Count>
    <DateTimeSang>2012-06-08T00:42:35.4562519-07:00</DateTimeSang>
    <Title>Safety Dance, The</Title>
    <Artist>Men Without Hats</Artist>
    <DiscID />
    <Pitch>0</Pitch>
    <Path>C:\Users\Karaoke\Music\karaoke\Dec-SC\dec sc\december sc convert final-1\Men Without Hats - Safety Dance, The.zip</Path>
    <Tempo>0</Tempo>
    <StartPoint>5.4625891946992864</StartPoint>
    <EndPoint>168.79400611620795</EndPoint>
  </dtSingerHistory>
  <dtSingerHistory>
    <Count>1</Count>
    <DateTimeSang>2012-06-10T23:31:55.7914402-07:00</DateTimeSang>
    <Title>Transmission</Title>
    <Artist>Joy Division</Artist>
    <DiscID />
    <Pitch>0</Pitch>
    <Path>C:\Users\Karaoke\Music\karaoke\LABELED 3\SUN DL\Joy Division - Transmission.zip</Path>
    <Tempo>0</Tempo>
    <StartPoint>0</StartPoint>
    <EndPoint>0</EndPoint>
  </dtSingerHistory>
  <dtSingerHistory>
    <Count>1</Count>
    <DateTimeSang>2012-06-11T01:00:31.9155051-07:00</DateTimeSang>
    <Title>Danger High Voltage</Title>
    <Artist>Electric Six</Artist>
    <DiscID />
    <Pitch>0</Pitch>
    <Path>C:\Users\Karaoke\Music\karaoke\2010 September\09.12\Electric Six - Danger High Voltage.zip</Path>
    <Tempo>0</Tempo>
    <StartPoint>0</StartPoint>
    <EndPoint>0</EndPoint>
  </dtSingerHistory>
  <dtSingerHistory>
    <Count>1</Count>
    <DateTimeSang>2012-06-16T00:11:00.3249245-07:00</DateTimeSang>
    <Title>True Faith</Title>
    <Artist>New Order</Artist>
    <DiscID />
    <Pitch>0</Pitch>
    <Path>C:\Users\Karaoke\Music\karaoke\LABELED 3\SUN\New Order - True Faith.zip</Path>
    <Tempo>0</Tempo>
    <StartPoint>0</StartPoint>
    <EndPoint>0</EndPoint>
  </dtSingerHistory>
  <dtSingerHistory>
    <Count>1</Count>
    <DateTimeSang>2012-06-21T22:14:46.4920097-07:00</DateTimeSang>
    <Title>In Crowd, The</Title>
    <Artist>Ferry, Bryan</Artist>
    <DiscID />
    <Pitch>0</Pitch>
    <Path>C:\Users\Karaoke\Music\karaoke\2011\2011 October\10-22\Ferry, Bryan - In Crowd, The.zip</Path>
    <Tempo>0</Tempo>
    <StartPoint>0</StartPoint>
    <EndPoint>0</EndPoint>
  </dtSingerHistory>
  <dtSingerHistory>
    <Count>1</Count>
    <DateTimeSang>2012-06-22T00:02:47.9557282-07:00</DateTimeSang>
    <Title>Delirious</Title>
    <Artist>Prince</Artist>
    <DiscID />
    <Pitch>0</Pitch>
    <Path>C:\Users\Karaoke\Music\karaoke\LABELED 3\SC\Prince - Delirious.zip</Path>
    <Tempo>0</Tempo>
    <StartPoint>0</StartPoint>
    <EndPoint>0</EndPoint>
  </dtSingerHistory>
  <dtSingerHistory>
    <Count>1</Count>
    <DateTimeSang>2012-06-23T00:05:45.7035948-07:00</DateTimeSang>
    <Title>Every Day Is Halloween</Title>
    <Artist>Ministry</Artist>
    <DiscID />
    <Pitch>0</Pitch>
    <Path>C:\Users\Karaoke\Music\karaoke\2011\2011 November\11-4\Ministry - Every Day Is Halloween.zip</Path>
    <Tempo>0</Tempo>
    <StartPoint>0</StartPoint>
    <EndPoint>0</EndPoint>
  </dtSingerHistory>
  <dtSingerHistory>
    <Count>1</Count>
    <DateTimeSang>2012-06-27T01:10:47.0110114-07:00</DateTimeSang>
    <Title>I Know You Want Me</Title>
    <Artist>Pitbull</Artist>
    <DiscID />
    <Pitch>0</Pitch>
    <Path>C:\Users\Karaoke\Music\karaoke\2010 December\12-31\Pitbull - I Know You Want Me.zip</Path>
    <Tempo>0</Tempo>
    <StartPoint>14.861250667443329</StartPoint>
    <EndPoint>264.95486904241824</EndPoint>
  </dtSingerHistory>
  <dtSingerHistory>
    <Count>1</Count>
    <DateTimeSang>2012-07-05T22:14:22.106101-07:00</DateTimeSang>
    <Title>Dirty Black Summer</Title>
    <Artist>Danzig</Artist>
    <DiscID />
    <Pitch>0</Pitch>
    <Path>C:\Users\Karaoke\Music\karaoke\2012\may\5-25\Danzig - Dirty Black Summer.zip</Path>
    <Tempo>0</Tempo>
    <StartPoint>0</StartPoint>
    <EndPoint>0</EndPoint>
  </dtSingerHistory>
  <dtSingerHistory>
    <Count>1</Count>
    <DateTimeSang>2012-07-05T22:53:18.4697333-07:00</DateTimeSang>
    <Title>Tenderness</Title>
    <Artist>General Public</Artist>
    <DiscID />
    <Pitch>0</Pitch>
    <Path>C:\Users\Karaoke\Music\karaoke\SC new adds\General Public - Tenderness.zip</Path>
    <Tempo>0</Tempo>
    <StartPoint>0</StartPoint>
    <EndPoint>0</EndPoint>
  </dtSingerHistory>
  <dtSingerHistory>
    <Count>1</Count>
    <DateTimeSang>2012-07-06T00:10:28.5455585-07:00</DateTimeSang>
    <Title>Girl U Want</Title>
    <Artist>Devo</Artist>
    <DiscID />
    <Pitch>0</Pitch>
    <Path>C:\Users\Karaoke\Music\karaoke\LABELED 3\ZOOM\Devo - Girl U Want.zip</Path>
    <Tempo>0</Tempo>
    <StartPoint>0</StartPoint>
    <EndPoint>0</EndPoint>
  </dtSingerHistory>
  <dtSingerHistory>
    <Count>1</Count>
    <DateTimeSang>2012-07-06T23:52:42.1479424-07:00</DateTimeSang>
    <Title>Love Cats</Title>
    <Artist>Cure, The</Artist>
    <DiscID />
    <Pitch>0</Pitch>
    <Path>C:\Users\Karaoke\Music\karaoke\LG\Cure, The - Love Cats.zip</Path>
    <Tempo>0</Tempo>
    <StartPoint>0</StartPoint>
    <EndPoint>0</EndPoint>
  </dtSingerHistory>
  <dtSingerHistory>
    <Count>1</Count>
    <DateTimeSang>2012-07-14T00:03:39.2244774-07:00</DateTimeSang>
    <Title>Everything Counts</Title>
    <Artist>Depeche Mode</Artist>
    <DiscID />
    <Pitch>0</Pitch>
    <Path>C:\Users\Karaoke\Music\karaoke\2011\2011 December\12-18\Depeche Mode - Everything Counts.zip</Path>
    <Tempo>0</Tempo>
    <StartPoint>0</StartPoint>
    <EndPoint>0</EndPoint>
  </dtSingerHistory>
  <dtSingerHistory>
    <Count>1</Count>
    <DateTimeSang>2012-07-19T20:44:34.0150544-07:00</DateTimeSang>
    <Title>Sweet '69</Title>
    <Artist>Babes In Toyland</Artist>
    <DiscID />
    <Pitch>0</Pitch>
    <Path>C:\Users\Karaoke\Music\karaoke\2012\jan\1-31\Babes In Toyland - Sweet '69.zip</Path>
    <Tempo>0</Tempo>
    <StartPoint>0</StartPoint>
    <EndPoint>0</EndPoint>
  </dtSingerHistory>
  <dtSingerHistory>
    <Count>1</Count>
    <DateTimeSang>2012-07-19T22:09:39.0170439-07:00</DateTimeSang>
    <Title>Awesome</Title>
    <Artist>Veruca Salt</Artist>
    <DiscID />
    <Pitch>0</Pitch>
    <Path>C:\Users\Karaoke\Music\karaoke\2012\feb\2-2\Veruca Salt - Awesome.zip</Path>
    <Tempo>0</Tempo>
    <StartPoint>0</StartPoint>
    <EndPoint>0</EndPoint>
  </dtSingerHistory>
  <dtSingerHistory>
    <Count>1</Count>
    <DateTimeSang>2012-07-22T00:53:49.8139889-07:00</DateTimeSang>
    <Title>I Can't Wait</Title>
    <Artist>Nu Shooz</Artist>
    <DiscID />
    <Pitch>0</Pitch>
    <Path>C:\Users\Karaoke\Music\karaoke\LABELED 3\SC\Nu Shooz - I Can't Wait.zip</Path>
    <Tempo>0</Tempo>
    <StartPoint>0</StartPoint>
    <EndPoint>0</EndPoint>
  </dtSingerHistory>
  <dtSingerHistory>
    <Count>1</Count>
    <DateTimeSang>2012-08-07T21:48:50.0665654-07:00</DateTimeSang>
    <Title>(They Long To Be) Close To You</Title>
    <Artist>Carpenters, The</Artist>
    <DiscID />
    <Pitch>0</Pitch>
    <Path>C:\Users\Karaoke\Music\karaoke\DK\Carpenters, The - (They Long To Be) Close To You.zip</Path>
    <Tempo>0</Tempo>
    <StartPoint>0</StartPoint>
    <EndPoint>0</EndPoint>
  </dtSingerHistory>
  <dtSingerHistory>
    <Count>1</Count>
    <DateTimeSang>2012-08-31T23:46:55.6761842-07:00</DateTimeSang>
    <Title>Oh! Darling</Title>
    <Artist>Beatles, The</Artist>
    <DiscID />
    <Pitch>0</Pitch>
    <Path>C:\Users\Karaoke\Music\karaoke\SC\Beatles, The - Oh! Darling.zip</Path>
    <Tempo>0</Tempo>
    <StartPoint>0</StartPoint>
    <EndPoint>0</EndPoint>
  </dtSingerHistory>
  <dtSingerHistory>
    <Count>1</Count>
    <DateTimeSang>2013-01-13T21:19:04.3882148-08:00</DateTimeSang>
    <Title>Big 10 Inch Record</Title>
    <Artist>Aerosmith</Artist>
    <DiscID />
    <Pitch>0</Pitch>
    <Path>C:\Users\Karaoke\Music\karaoke\LABELED 3\Radio Starz\Aerosmith - Big 10 Inch Record.zip</Path>
    <Tempo>0</Tempo>
    <StartPoint>0</StartPoint>
    <EndPoint>0</EndPoint>
  </dtSingerHistory>
  <dtSingerHistory>
    <Count>1</Count>
    <DateTimeSang>2013-01-13T22:24:43.7985362-08:00</DateTimeSang>
    <Title>A##hole</Title>
    <Artist>Leary, Denis</Artist>
    <DiscID />
    <Pitch>0</Pitch>
    <Path>C:\Users\Karaoke\Music\karaoke\SC new adds\Leary, Denis - A##hole.zip</Path>
    <Tempo>0</Tempo>
    <StartPoint>0</StartPoint>
    <EndPoint>0</EndPoint>
  </dtSingerHistory>
  <dtSingerHistory>
    <Count>1</Count>
    <DateTimeSang>2013-04-18T22:05:10.0083785-07:00</DateTimeSang>
    <Title>Spellbound</Title>
    <Artist>Siouxsie &amp; The Banshees</Artist>
    <DiscID />
    <Pitch>0</Pitch>
    <Path>C:\Users\Karaoke\Music\karaoke\2013\1-9\Siouxsie &amp; The Banshees - Spellbound.zip</Path>
    <Tempo>0</Tempo>
    <StartPoint>0</StartPoint>
    <EndPoint>0</EndPoint>
  </dtSingerHistory>
  <dtSingerHistory>
    <Count>1</Count>
    <DateTimeSang>2013-05-08T22:33:20.476224-07:00</DateTimeSang>
    <Title>John The Revelator</Title>
    <Artist>Depeche Mode</Artist>
    <DiscID />
    <Pitch>0</Pitch>
    <Path>C:\Users\Karaoke\Music\karaoke\2013\2-7\Depeche Mode - John The Revelator.zip</Path>
    <Tempo>0</Tempo>
    <StartPoint>0</StartPoint>
    <EndPoint>0</EndPoint>
  </dtSingerHistory>
  <dtSingerHistory>
    <Count>1</Count>
    <DateTimeSang>2013-05-08T23:21:41.6111594-07:00</DateTimeSang>
    <Title>Midlife Crisis</Title>
    <Artist>Faith No More</Artist>
    <DiscID />
    <Pitch>0</Pitch>
    <Path>C:\Users\Karaoke\Music\karaoke\LABELED 3\SUN\Faith No More - Midlife Crisis.zip</Path>
    <Tempo>0</Tempo>
    <StartPoint>0</StartPoint>
    <EndPoint>0</EndPoint>
  </dtSingerHistory>
</dsSingerHistory>