<?xml version="1.0" standalone="yes"?>
<dsSingerHistory xmlns="http://tempuri.org/dsSingerHistory.xsd">
  <dtSingerHistory>
    <Count>1</Count>
    <DateTimeSang>2011-08-18T22:27:15.2042986-07:00</DateTimeSang>
    <Title>Your Song</Title>
    <Artist>John, Elton</Artist>
    <DiscID />
    <Pitch>0</Pitch>
    <Path>C:\Users\Karaoke\Music\karaoke\SC\John, Elton - Your Song.zip</Path>
    <Tempo>0</Tempo>
    <StartPoint>0</StartPoint>
    <EndPoint>0</EndPoint>
  </dtSingerHistory>
  <dtSingerHistory>
    <Count>1</Count>
    <DateTimeSang>2011-08-18T23:57:10.5448944-07:00</DateTimeSang>
    <Title>Cowboy</Title>
    <Artist>Kid Rock</Artist>
    <DiscID />
    <Pitch>0</Pitch>
    <Path>C:\Users\Karaoke\Music\karaoke\SC new adds\Kid Rock - Cowboy.zip</Path>
    <Tempo>0</Tempo>
    <StartPoint>0</StartPoint>
    <EndPoint>0</EndPoint>
  </dtSingerHistory>
</dsSingerHistory>