<?xml version="1.0" standalone="yes"?>
<dsSingerHistory xmlns="http://tempuri.org/dsSingerHistory.xsd">
  <dtSingerHistory>
    <Count>1</Count>
    <DateTimeSang>2011-09-04T22:11:05.3771912-07:00</DateTimeSang>
    <Title>Clint Eastwood</Title>
    <Artist>Gorillaz</Artist>
    <DiscID />
    <Pitch>0</Pitch>
    <Path>C:\Users\Karaoke\Music\karaoke\LABELED 3\SC\Gorillaz - Clint Eastwood.zip</Path>
    <Tempo>0</Tempo>
    <StartPoint>0</StartPoint>
    <EndPoint>0</EndPoint>
  </dtSingerHistory>
  <dtSingerHistory>
    <Count>1</Count>
    <DateTimeSang>2011-09-05T00:30:54.3460127-07:00</DateTimeSang>
    <Title>Ain't No Rest For The Wicked</Title>
    <Artist>Cage The Elephant</Artist>
    <DiscID />
    <Pitch>0</Pitch>
    <Path>C:\Users\Karaoke\Music\karaoke\LABELED 3\SUN\Cage The Elephant - Ain't No Rest For The Wicked.zip</Path>
    <Tempo>0</Tempo>
    <StartPoint>0</StartPoint>
    <EndPoint>0</EndPoint>
  </dtSingerHistory>
</dsSingerHistory>