<?xml version="1.0" standalone="yes"?>
<dsSingerHistory xmlns="http://tempuri.org/dsSingerHistory.xsd">
  <dtSingerHistory>
    <Count>1</Count>
    <DateTimeSang>2010-01-22T22:33:38.3233755-08:00</DateTimeSang>
    <Title>Settlin'</Title>
    <Artist>Sugarland</Artist>
    <DiscID />
    <Pitch>0</Pitch>
    <Path>C:\Users\Karaoke\Music\karaoke\2009 July\07.09\Sugarland - Settlin'.zip</Path>
    <Tempo>0</Tempo>
    <StartPoint>0</StartPoint>
    <EndPoint>0</EndPoint>
  </dtSingerHistory>
  <dtSingerHistory>
    <Count>1</Count>
    <DateTimeSang>2010-01-22T23:44:57.2251147-08:00</DateTimeSang>
    <Title>Redneck Woman</Title>
    <Artist>Wilson, Gretchen</Artist>
    <DiscID />
    <Pitch>0</Pitch>
    <Path>C:\Users\Karaoke\Music\karaoke\country\Wilson, Gretchen - Redneck Woman.zip</Path>
    <Tempo>0</Tempo>
    <StartPoint>0</StartPoint>
    <EndPoint>0</EndPoint>
  </dtSingerHistory>
  <dtSingerHistory>
    <Count>2</Count>
    <DateTimeSang>2012-03-10T00:24:21.1126154-08:00</DateTimeSang>
    <Title>I Touch Myself</Title>
    <Artist>Divinyls, The</Artist>
    <DiscID />
    <Pitch>0</Pitch>
    <Path>C:\Users\Karaoke\Music\karaoke\LABELED\ZOOM\Divinyls, The - I Touch Myself.zip</Path>
    <Tempo>0</Tempo>
    <StartPoint>0</StartPoint>
    <EndPoint>0</EndPoint>
  </dtSingerHistory>
  <dtSingerHistory>
    <Count>1</Count>
    <DateTimeSang>2010-04-03T00:08:57.986794-07:00</DateTimeSang>
    <Title>Gunpowder And Lead</Title>
    <Artist>Lambert, Miranda</Artist>
    <DiscID />
    <Pitch>0</Pitch>
    <Path>C:\Users\Karaoke\Music\karaoke\LABELED 3\SBI\Lambert, Miranda - Gunpowder And Lead.zip</Path>
    <Tempo>0</Tempo>
    <StartPoint>0</StartPoint>
    <EndPoint>0</EndPoint>
  </dtSingerHistory>
  <dtSingerHistory>
    <Count>1</Count>
    <DateTimeSang>2010-05-01T00:46:04.6208767-07:00</DateTimeSang>
    <Title>Alejandro</Title>
    <Artist>Lady GaGa</Artist>
    <DiscID />
    <Pitch>0</Pitch>
    <Path>C:\Users\Karaoke\Music\karaoke\2010 February\02-04\Lady GaGa - Alejandro.zip</Path>
    <Tempo>0</Tempo>
    <StartPoint>0</StartPoint>
    <EndPoint>0</EndPoint>
  </dtSingerHistory>
  <dtSingerHistory>
    <Count>1</Count>
    <DateTimeSang>2010-07-01T22:58:21.820783-07:00</DateTimeSang>
    <Title>Respect</Title>
    <Artist>Franklin, Aretha</Artist>
    <DiscID />
    <Pitch>0</Pitch>
    <Path>C:\Users\Karaoke\Music\karaoke\Dec-SC\dec sc\december sc convert final-2\Franklin, Aretha - Respect.zip</Path>
    <Tempo>0</Tempo>
    <StartPoint>0</StartPoint>
    <EndPoint>0</EndPoint>
  </dtSingerHistory>
  <dtSingerHistory>
    <Count>1</Count>
    <DateTimeSang>2010-07-03T00:56:52.6089599-07:00</DateTimeSang>
    <Title>Miranda_Lambert_White_Liar_54917.zip</Title>
    <Artist />
    <DiscID />
    <Pitch>0</Pitch>
    <Path>C:\Users\Karaoke\Desktop\07-01\Miranda_Lambert_White_Liar_54917.zip</Path>
    <Tempo>0</Tempo>
    <StartPoint>0</StartPoint>
    <EndPoint>0</EndPoint>
  </dtSingerHistory>
  <dtSingerHistory>
    <Count>2</Count>
    <DateTimeSang>2011-05-07T00:11:22.6340791-07:00</DateTimeSang>
    <Title>Something More</Title>
    <Artist>Sugarland</Artist>
    <DiscID />
    <Pitch>0</Pitch>
    <Path>C:\Users\Karaoke\Music\karaoke\LABELED 3\Top Hits\Sugarland - Something More.zip</Path>
    <Tempo>0</Tempo>
    <StartPoint>0</StartPoint>
    <EndPoint>0</EndPoint>
  </dtSingerHistory>
  <dtSingerHistory>
    <Count>1</Count>
    <DateTimeSang>2010-07-22T23:16:46.846894-07:00</DateTimeSang>
    <Title>Jesus, Take The Wheel</Title>
    <Artist>Underwood, Carrie</Artist>
    <DiscID />
    <Pitch>0</Pitch>
    <Path>C:\Users\Karaoke\Music\karaoke\LABELED 3\SUN\Underwood, Carrie - Jesus, Take The Wheel.zip</Path>
    <Tempo>0</Tempo>
    <StartPoint>0</StartPoint>
    <EndPoint>0</EndPoint>
  </dtSingerHistory>
  <dtSingerHistory>
    <Count>1</Count>
    <DateTimeSang>2010-07-23T01:08:29.2662505-07:00</DateTimeSang>
    <Title>Flashdance... What A Feeling</Title>
    <Artist>Cara, Irene</Artist>
    <DiscID />
    <Pitch>0</Pitch>
    <Path>C:\Users\Karaoke\Music\karaoke\SC Foundations\Cara, Irene - Flashdance... What A Feeling.zip</Path>
    <Tempo>0</Tempo>
    <StartPoint>0</StartPoint>
    <EndPoint>0</EndPoint>
  </dtSingerHistory>
  <dtSingerHistory>
    <Count>3</Count>
    <DateTimeSang>2011-07-23T01:22:50.5100688-07:00</DateTimeSang>
    <Title>Cowboy Casanova</Title>
    <Artist>Underwood, Carrie</Artist>
    <DiscID />
    <Pitch>0</Pitch>
    <Path>C:\Users\Karaoke\Music\karaoke\2010 February\2-18\Underwood, Carrie - Cowboy Casanova.zip</Path>
    <Tempo>0</Tempo>
    <StartPoint>0</StartPoint>
    <EndPoint>0</EndPoint>
  </dtSingerHistory>
  <dtSingerHistory>
    <Count>2</Count>
    <DateTimeSang>2012-07-28T00:38:39.7720901-07:00</DateTimeSang>
    <Title>My Favorite Mistake</Title>
    <Artist>Crow, Sheryl</Artist>
    <DiscID />
    <Pitch>0</Pitch>
    <Path>C:\Users\Karaoke\Music\karaoke\Dec-SC\dec sc\december sc convert final-2\Crow, Sheryl - My Favorite Mistake.zip</Path>
    <Tempo>0</Tempo>
    <StartPoint>0</StartPoint>
    <EndPoint>0</EndPoint>
  </dtSingerHistory>
  <dtSingerHistory>
    <Count>1</Count>
    <DateTimeSang>2010-09-02T00:13:49.5823516-07:00</DateTimeSang>
    <Title>Friends In Low Places</Title>
    <Artist>Brooks, Garth</Artist>
    <DiscID />
    <Pitch>0</Pitch>
    <Path>C:\Users\Karaoke\Music\karaoke\CHB\Brooks, Garth - Friends In Low Places.zip</Path>
    <Tempo>0</Tempo>
    <StartPoint>0</StartPoint>
    <EndPoint>0</EndPoint>
  </dtSingerHistory>
  <dtSingerHistory>
    <Count>1</Count>
    <DateTimeSang>2010-09-24T23:08:50.1455602-07:00</DateTimeSang>
    <Title>Private Dancer</Title>
    <Artist>Turner, Tina</Artist>
    <DiscID />
    <Pitch>0</Pitch>
    <Path>C:\Users\Karaoke\Music\karaoke\LABELED 3\SC\Turner, Tina - Private Dancer.zip</Path>
    <Tempo>0</Tempo>
    <StartPoint>0</StartPoint>
    <EndPoint>0</EndPoint>
  </dtSingerHistory>
  <dtSingerHistory>
    <Count>1</Count>
    <DateTimeSang>2011-04-22T23:43:56.6623596-07:00</DateTimeSang>
    <Title>When Doves Cry</Title>
    <Artist>Prince</Artist>
    <DiscID />
    <Pitch>0</Pitch>
    <Path>C:\Users\Karaoke\Music\karaoke\LG\Prince - When Doves Cry.zip</Path>
    <Tempo>0</Tempo>
    <StartPoint>0</StartPoint>
    <EndPoint>0</EndPoint>
  </dtSingerHistory>
  <dtSingerHistory>
    <Count>1</Count>
    <DateTimeSang>2011-08-13T00:15:10.86009-07:00</DateTimeSang>
    <Title>Britney_Spears_-_I_Love_Rock_'n_Roll_-_G11800.ZIP</Title>
    <Artist />
    <DiscID />
    <Pitch>0</Pitch>
    <Path>C:\Users\Karaoke\Desktop\7-20\Britney_Spears_-_I_Love_Rock_'n_Roll_-_G11800.ZIP</Path>
    <Tempo>0</Tempo>
    <StartPoint>0</StartPoint>
    <EndPoint>0</EndPoint>
  </dtSingerHistory>
  <dtSingerHistory>
    <Count>1</Count>
    <DateTimeSang>2011-11-19T00:38:12.5667406-08:00</DateTimeSang>
    <Title>Party Rock Anthem (Feat. Lauren Bennett And Goonrock)</Title>
    <Artist>LMFAO</Artist>
    <DiscID />
    <Pitch>0</Pitch>
    <Path>C:\Users\Karaoke\Music\karaoke\2011\2011 June\6-10\LMFAO - Party Rock Anthem (Feat. Lauren Bennett And Goonrock).zip</Path>
    <Tempo>0</Tempo>
    <StartPoint>0</StartPoint>
    <EndPoint>0</EndPoint>
  </dtSingerHistory>
  <dtSingerHistory>
    <Count>1</Count>
    <DateTimeSang>2011-12-30T21:43:30.8937841-08:00</DateTimeSang>
    <Title>Me &amp; Bobby McGee</Title>
    <Artist>Joplin, Janis</Artist>
    <DiscID />
    <Pitch>0</Pitch>
    <Path>C:\Users\Karaoke\Music\karaoke\Dec-SC\dec sc\december sc convert final 3\Joplin, Janis - Me &amp; Bobby McGee.zip</Path>
    <Tempo>0</Tempo>
    <StartPoint>0</StartPoint>
    <EndPoint>0</EndPoint>
  </dtSingerHistory>
  <dtSingerHistory>
    <Count>1</Count>
    <DateTimeSang>2011-12-30T22:44:42.8258066-08:00</DateTimeSang>
    <Title>What's Up</Title>
    <Artist>Four Non Blondes</Artist>
    <DiscID />
    <Pitch>0</Pitch>
    <Path>C:\Users\Karaoke\Music\karaoke\Supercore 2006\Four Non Blondes - What's Up.zip</Path>
    <Tempo>0</Tempo>
    <StartPoint>0</StartPoint>
    <EndPoint>0</EndPoint>
  </dtSingerHistory>
  <dtSingerHistory>
    <Count>1</Count>
    <DateTimeSang>2012-01-21T00:42:34.9056505-08:00</DateTimeSang>
    <Title>Oops! I Did It Again</Title>
    <Artist>Spears, Britney</Artist>
    <DiscID />
    <Pitch>0</Pitch>
    <Path>C:\Users\Karaoke\Music\karaoke\CHB\Spears, Britney - Oops! I Did It Again.zip</Path>
    <Tempo>0</Tempo>
    <StartPoint>0</StartPoint>
    <EndPoint>0</EndPoint>
  </dtSingerHistory>
  <dtSingerHistory>
    <Count>1</Count>
    <DateTimeSang>2012-02-27T00:19:41.3647178-08:00</DateTimeSang>
    <Title>Toxic</Title>
    <Artist>Spears, Britney</Artist>
    <DiscID />
    <Pitch>0</Pitch>
    <Path>C:\Users\Karaoke\Music\karaoke\CHB\Spears, Britney - Toxic.zip</Path>
    <Tempo>0</Tempo>
    <StartPoint>0</StartPoint>
    <EndPoint>0</EndPoint>
  </dtSingerHistory>
  <dtSingerHistory>
    <Count>2</Count>
    <DateTimeSang>2012-05-26T00:43:17.6544238-07:00</DateTimeSang>
    <Title>Before He Cheats</Title>
    <Artist>Underwood, Carrie</Artist>
    <DiscID />
    <Pitch>0</Pitch>
    <Path>C:\Users\Karaoke\Music\karaoke\SBI\Underwood, Carrie - Before He Cheats.zip</Path>
    <Tempo>0</Tempo>
    <StartPoint>0</StartPoint>
    <EndPoint>0</EndPoint>
  </dtSingerHistory>
  <dtSingerHistory>
    <Count>1</Count>
    <DateTimeSang>2012-03-09T22:42:58.0216825-08:00</DateTimeSang>
    <Title>Trouble With Love Is, The</Title>
    <Artist>Clarkson, Kelly</Artist>
    <DiscID />
    <Pitch>0</Pitch>
    <Path>C:\Users\Karaoke\Music\karaoke\CHB\Clarkson, Kelly - Trouble With Love Is, The.zip</Path>
    <Tempo>0</Tempo>
    <StartPoint>0</StartPoint>
    <EndPoint>0</EndPoint>
  </dtSingerHistory>
  <dtSingerHistory>
    <Count>1</Count>
    <DateTimeSang>2012-04-29T22:08:17.929245-07:00</DateTimeSang>
    <Title>Born On The Bayou</Title>
    <Artist>Creedence Clearwater Revival</Artist>
    <DiscID />
    <Pitch>0</Pitch>
    <Path>C:\Users\Karaoke\Music\karaoke\sgb\Creedence Clearwater Revival - Born On The Bayou.zip</Path>
    <Tempo>0</Tempo>
    <StartPoint>0</StartPoint>
    <EndPoint>0</EndPoint>
  </dtSingerHistory>
  <dtSingerHistory>
    <Count>1</Count>
    <DateTimeSang>2012-04-29T23:43:31.8014415-07:00</DateTimeSang>
    <Title>Gimme Three Steps</Title>
    <Artist>Lynyrd Skynyrd</Artist>
    <DiscID />
    <Pitch>0</Pitch>
    <Path>C:\Users\Karaoke\Music\karaoke\Dec-SC\dec sc\december sc convert final-1\Lynyrd Skynyrd - Gimme Three Steps.zip</Path>
    <Tempo>0</Tempo>
    <StartPoint>0</StartPoint>
    <EndPoint>0</EndPoint>
  </dtSingerHistory>
  <dtSingerHistory>
    <Count>1</Count>
    <DateTimeSang>2012-05-04T23:20:37.5515087-07:00</DateTimeSang>
    <Title>Stay (I Missed You)</Title>
    <Artist>Loeb, Lisa</Artist>
    <DiscID />
    <Pitch>0</Pitch>
    <Path>C:\Users\Karaoke\Music\karaoke\LABELED 3\SBI\Loeb, Lisa - Stay (I Missed You).zip</Path>
    <Tempo>0</Tempo>
    <StartPoint>0</StartPoint>
    <EndPoint>0</EndPoint>
  </dtSingerHistory>
  <dtSingerHistory>
    <Count>1</Count>
    <DateTimeSang>2012-05-25T23:44:46.1845792-07:00</DateTimeSang>
    <Title>Last Friday Night (T.G.I.F)</Title>
    <Artist>Perry, Katy</Artist>
    <DiscID />
    <Pitch>0</Pitch>
    <Path>C:\Users\Karaoke\Music\karaoke\2011\2011 July\7-19\Perry, Katy - Last Friday Night (T.G.I.F).zip</Path>
    <Tempo>0</Tempo>
    <StartPoint>0</StartPoint>
    <EndPoint>0</EndPoint>
  </dtSingerHistory>
  <dtSingerHistory>
    <Count>1</Count>
    <DateTimeSang>2012-06-01T23:52:43.378672-07:00</DateTimeSang>
    <Title>Blackbird</Title>
    <Artist>Beatles, The</Artist>
    <DiscID />
    <Pitch>0</Pitch>
    <Path>C:\Users\Karaoke\Music\karaoke\LABELED 3\SBI\Beatles, The - Blackbird.zip</Path>
    <Tempo>0</Tempo>
    <StartPoint>0</StartPoint>
    <EndPoint>0</EndPoint>
  </dtSingerHistory>
  <dtSingerHistory>
    <Count>1</Count>
    <DateTimeSang>2012-07-06T23:23:53.8520895-07:00</DateTimeSang>
    <Title>You Were Meant For Me</Title>
    <Artist>Jewel</Artist>
    <DiscID />
    <Pitch>0</Pitch>
    <Path>C:\Users\Karaoke\Music\karaoke\Dec-SC\dec sc\december sc convert final-2\Jewel - You Were Meant For Me.zip</Path>
    <Tempo>0</Tempo>
    <StartPoint>0</StartPoint>
    <EndPoint>0</EndPoint>
  </dtSingerHistory>
  <dtSingerHistory>
    <Count>1</Count>
    <DateTimeSang>2012-09-18T23:39:01.9434395-07:00</DateTimeSang>
    <Title>Empire State Of Mind (Feat. Alicia Keys)</Title>
    <Artist>Jay-Z</Artist>
    <DiscID />
    <Pitch>0</Pitch>
    <Path>C:\Users\Karaoke\Music\karaoke\2010 August\08-26\Jay-Z - Empire State Of Mind (Feat. Alicia Keys).zip</Path>
    <Tempo>0</Tempo>
    <StartPoint>0</StartPoint>
    <EndPoint>0</EndPoint>
  </dtSingerHistory>
  <dtSingerHistory>
    <Count>1</Count>
    <DateTimeSang>2012-09-23T21:44:37.405285-07:00</DateTimeSang>
    <Title>Summer Of '69</Title>
    <Artist>Adams, Bryan</Artist>
    <DiscID />
    <Pitch>0</Pitch>
    <Path>C:\Users\Karaoke\Music\karaoke\2011\2011 August\8-28\Adams, Bryan - Summer Of '69.zip</Path>
    <Tempo>0</Tempo>
    <StartPoint>0</StartPoint>
    <EndPoint>0</EndPoint>
  </dtSingerHistory>
  <dtSingerHistory>
    <Count>1</Count>
    <DateTimeSang>2012-09-23T23:22:49.1342727-07:00</DateTimeSang>
    <Title>Hungry Like The Wolf</Title>
    <Artist>Duran Duran</Artist>
    <DiscID />
    <Pitch>0</Pitch>
    <Path>C:\Users\Karaoke\Music\karaoke\Dec-SC\dec sc\december sc convert final-1\Duran Duran - Hungry Like The Wolf.zip</Path>
    <Tempo>0</Tempo>
    <StartPoint>0</StartPoint>
    <EndPoint>0</EndPoint>
  </dtSingerHistory>
  <dtSingerHistory>
    <Count>2</Count>
    <DateTimeSang>2012-11-27T22:38:14.5304043-08:00</DateTimeSang>
    <Title>Ego</Title>
    <Artist>Beyonce</Artist>
    <DiscID />
    <Pitch>0</Pitch>
    <Path>C:\Users\Karaoke\Music\karaoke\2012\july\7-13\Beyonce - Ego.zip</Path>
    <Tempo>0</Tempo>
    <StartPoint>0</StartPoint>
    <EndPoint>0</EndPoint>
  </dtSingerHistory>
  <dtSingerHistory>
    <Count>1</Count>
    <DateTimeSang>2012-11-27T22:53:31.3208417-08:00</DateTimeSang>
    <Title>Can't Take My Eyes Off Of You</Title>
    <Artist>Hill, Lauryn</Artist>
    <DiscID />
    <Pitch>0</Pitch>
    <Path>C:\Users\Karaoke\Music\karaoke\sgb\Hill, Lauryn - Can't Take My Eyes Off Of You.zip</Path>
    <Tempo>0</Tempo>
    <StartPoint>0</StartPoint>
    <EndPoint>0</EndPoint>
  </dtSingerHistory>
  <dtSingerHistory>
    <Count>1</Count>
    <DateTimeSang>2012-11-27T23:17:27.9060097-08:00</DateTimeSang>
    <Title>All I Want Is You (Feat. J. Cole)</Title>
    <Artist>Miguel</Artist>
    <DiscID />
    <Pitch>0</Pitch>
    <Path>C:\Users\Karaoke\Music\karaoke\2010 September\9.09\Miguel - All I Want Is You (Feat. J. Cole).zip</Path>
    <Tempo>0</Tempo>
    <StartPoint>0</StartPoint>
    <EndPoint>0</EndPoint>
  </dtSingerHistory>
  <dtSingerHistory>
    <Count>1</Count>
    <DateTimeSang>2013-03-10T22:14:40.0275707-07:00</DateTimeSang>
    <Title>Bye Bye</Title>
    <Artist>Messina, Jo Dee</Artist>
    <DiscID />
    <Pitch>0</Pitch>
    <Path>C:\Users\Karaoke\Music\karaoke\CHB\Messina, Jo Dee - Bye Bye.zip</Path>
    <Tempo>0</Tempo>
    <StartPoint>0</StartPoint>
    <EndPoint>0</EndPoint>
  </dtSingerHistory>
  <dtSingerHistory>
    <Count>1</Count>
    <DateTimeSang>2013-04-09T22:01:25.8785408-07:00</DateTimeSang>
    <Title>Mary_J._Blige_-_Sweet_Thing_-_G02230.ZIP</Title>
    <Artist />
    <DiscID />
    <Pitch>0</Pitch>
    <Path>C:\Users\Karaoke\Desktop\04-05\Mary_J._Blige_-_Sweet_Thing_-_G02230.ZIP</Path>
    <Tempo>0</Tempo>
    <StartPoint>0</StartPoint>
    <EndPoint>0</EndPoint>
  </dtSingerHistory>
  <dtSingerHistory>
    <Count>3</Count>
    <DateTimeSang>2013-06-05T00:22:05.0185715-07:00</DateTimeSang>
    <Title>Neon Moon</Title>
    <Artist>Brooks &amp; Dunn</Artist>
    <DiscID />
    <Pitch>0</Pitch>
    <Path>C:\Users\Karaoke\Music\karaoke\Dec-SC\December SC Country\Brooks &amp; Dunn - Neon Moon.zip</Path>
    <Tempo>0</Tempo>
    <StartPoint>0</StartPoint>
    <EndPoint>0</EndPoint>
  </dtSingerHistory>
  <dtSingerHistory>
    <Count>1</Count>
    <DateTimeSang>2013-04-16T22:24:01.7882585-07:00</DateTimeSang>
    <Title>Landslide</Title>
    <Artist>Dixie Chicks</Artist>
    <DiscID />
    <Pitch>0</Pitch>
    <Path>C:\Users\Karaoke\Music\karaoke\SC new adds\Dixie Chicks - Landslide.zip</Path>
    <Tempo>0</Tempo>
    <StartPoint>0</StartPoint>
    <EndPoint>0</EndPoint>
  </dtSingerHistory>
  <dtSingerHistory>
    <Count>1</Count>
    <DateTimeSang>2013-04-16T23:10:32.4888775-07:00</DateTimeSang>
    <Title>Notorious_B.I.G._-_Juicy_(It's_All_Good)_-_SFDT-1394.ZIP</Title>
    <Artist />
    <DiscID />
    <Pitch>0</Pitch>
    <Path>C:\Users\Karaoke\Desktop\04-05\Notorious_B.I.G._-_Juicy_(It's_All_Good)_-_SFDT-1394.ZIP</Path>
    <Tempo>0</Tempo>
    <StartPoint>0</StartPoint>
    <EndPoint>0</EndPoint>
  </dtSingerHistory>
  <dtSingerHistory>
    <Count>1</Count>
    <DateTimeSang>2013-04-17T00:41:08.2377845-07:00</DateTimeSang>
    <Title>Ho Hey</Title>
    <Artist>Lumineers, The</Artist>
    <DiscID />
    <Pitch>0</Pitch>
    <Path>C:\Users\Karaoke\Music\karaoke\2012\august\8-5\Lumineers, The - Ho Hey.zip</Path>
    <Tempo>0</Tempo>
    <StartPoint>0</StartPoint>
    <EndPoint>0</EndPoint>
  </dtSingerHistory>
  <dtSingerHistory>
    <Count>1</Count>
    <DateTimeSang>2013-04-17T01:28:34.9156052-07:00</DateTimeSang>
    <Title>Lady_Antebellum_American_Honey_64198.zip</Title>
    <Artist />
    <DiscID />
    <Pitch>0</Pitch>
    <Path>C:\Users\Karaoke\Desktop\04-05\Lady_Antebellum_American_Honey_64198.zip</Path>
    <Tempo>0</Tempo>
    <StartPoint>0</StartPoint>
    <EndPoint>0</EndPoint>
  </dtSingerHistory>
  <dtSingerHistory>
    <Count>1</Count>
    <DateTimeSang>2013-04-23T21:41:06.7061005-07:00</DateTimeSang>
    <Title>Picture (Feat. Sheryl Crow)</Title>
    <Artist>Kid Rock</Artist>
    <DiscID />
    <Pitch>0</Pitch>
    <Path>C:\Users\Karaoke\Music\karaoke\CHB\Kid Rock - Picture (Feat. Sheryl Crow).zip</Path>
    <Tempo>0</Tempo>
    <StartPoint>0</StartPoint>
    <EndPoint>0</EndPoint>
  </dtSingerHistory>
  <dtSingerHistory>
    <Count>1</Count>
    <DateTimeSang>2013-04-24T00:44:40.1750349-07:00</DateTimeSang>
    <Title>Rude Boy</Title>
    <Artist>Rihanna</Artist>
    <DiscID />
    <Pitch>0</Pitch>
    <Path>C:\Users\Karaoke\Music\karaoke\2010 February\02-04\Rihanna - Rude Boy.zip</Path>
    <Tempo>0</Tempo>
    <StartPoint>0</StartPoint>
    <EndPoint>0</EndPoint>
  </dtSingerHistory>
  <dtSingerHistory>
    <Count>1</Count>
    <DateTimeSang>2013-05-08T01:10:56.0957198-07:00</DateTimeSang>
    <Title>Landslide</Title>
    <Artist>Fleetwood Mac</Artist>
    <DiscID />
    <Pitch>0</Pitch>
    <Path>C:\Users\Karaoke\Music\karaoke\LABELED 2\SC\Fleetwood Mac - Landslide.zip</Path>
    <Tempo>0</Tempo>
    <StartPoint>0</StartPoint>
    <EndPoint>0</EndPoint>
  </dtSingerHistory>
  <dtSingerHistory>
    <Count>1</Count>
    <DateTimeSang>2013-05-22T01:25:23.5892555-07:00</DateTimeSang>
    <Title>Sweet Thing</Title>
    <Artist>Blige, Mary J.</Artist>
    <DiscID />
    <Pitch>0</Pitch>
    <Path>C:\Users\Karaoke\Music\karaoke\2013\5-08 (fix)\Blige, Mary J. - Sweet Thing.zip</Path>
    <Tempo>0</Tempo>
    <StartPoint>0</StartPoint>
    <EndPoint>0</EndPoint>
  </dtSingerHistory>
  <dtSingerHistory>
    <Count>1</Count>
    <DateTimeSang>2013-05-31T00:04:18.8577398-07:00</DateTimeSang>
    <Title>American Honey</Title>
    <Artist>Lady Antebellum</Artist>
    <DiscID />
    <Pitch>0</Pitch>
    <Path>C:\Users\Karaoke\Music\karaoke\2013\5-08 (fix)\Lady Antebellum - American Honey.zip</Path>
    <Tempo>0</Tempo>
    <StartPoint>0</StartPoint>
    <EndPoint>0</EndPoint>
  </dtSingerHistory>
  <dtSingerHistory>
    <Count>4</Count>
    <DateTimeSang>2013-06-19T01:39:20.8075566-07:00</DateTimeSang>
    <Title>Stay</Title>
    <Artist>Rihanna</Artist>
    <DiscID />
    <Pitch>0</Pitch>
    <Path>C:\Users\Karaoke\Music\karaoke\2013\5-08 (fix)\Rihanna - Stay.zip</Path>
    <Tempo>0</Tempo>
    <StartPoint>0</StartPoint>
    <EndPoint>0</EndPoint>
  </dtSingerHistory>
  <dtSingerHistory>
    <Count>1</Count>
    <DateTimeSang>2013-06-06T01:12:09.0358586-07:00</DateTimeSang>
    <Title>Can't Buy Me Love</Title>
    <Artist>Beatles, The</Artist>
    <DiscID />
    <Pitch>0</Pitch>
    <Path>C:\Users\Karaoke\Music\karaoke\LABELED 3\ZOOM DL\Beatles, The - Can't Buy Me Love.zip</Path>
    <Tempo>0</Tempo>
    <StartPoint>0</StartPoint>
    <EndPoint>0</EndPoint>
  </dtSingerHistory>
  <dtSingerHistory>
    <Count>1</Count>
    <DateTimeSang>2013-06-06T21:59:33.5527495-07:00</DateTimeSang>
    <Title>Home</Title>
    <Artist>Phillips, Phillip</Artist>
    <DiscID />
    <Pitch>0</Pitch>
    <Path>C:\Users\Karaoke\Music\karaoke\2012\august\8-30\Phillips, Phillip - Home.zip</Path>
    <Tempo>0</Tempo>
    <StartPoint>0</StartPoint>
    <EndPoint>0</EndPoint>
  </dtSingerHistory>
</dsSingerHistory>