<?xml version="1.0" standalone="yes"?>
<dsSingerHistory xmlns="http://tempuri.org/dsSingerHistory.xsd">
  <dtSingerHistory>
    <Count>1</Count>
    <DateTimeSang>2010-04-16T22:17:31.5634885-07:00</DateTimeSang>
    <Title>Forever In Blue Jeans</Title>
    <Artist>Diamond, Neil</Artist>
    <DiscID />
    <Pitch>0</Pitch>
    <Path>C:\Users\Karaoke\Music\karaoke\LABELED 3\BS\Diamond, Neil - Forever In Blue Jeans.zip</Path>
    <Tempo>0</Tempo>
    <StartPoint>0</StartPoint>
    <EndPoint>0</EndPoint>
  </dtSingerHistory>
  <dtSingerHistory>
    <Count>1</Count>
    <DateTimeSang>2010-04-16T22:50:37.6880884-07:00</DateTimeSang>
    <Title>Jeremy</Title>
    <Artist>Pearl Jam</Artist>
    <DiscID />
    <Pitch>0</Pitch>
    <Path>C:\Users\Karaoke\Music\karaoke\LABELED 3\NuTech\Pearl Jam - Jeremy.zip</Path>
    <Tempo>0</Tempo>
    <StartPoint>0</StartPoint>
    <EndPoint>0</EndPoint>
  </dtSingerHistory>
  <dtSingerHistory>
    <Count>1</Count>
    <DateTimeSang>2010-04-16T23:58:41.8056865-07:00</DateTimeSang>
    <Title>Patience</Title>
    <Artist>Guns 'N' Roses</Artist>
    <DiscID />
    <Pitch>0</Pitch>
    <Path>C:\Users\Karaoke\Music\karaoke\LABELED 3\ZOOM DL\Guns 'N' Roses - Patience.zip</Path>
    <Tempo>0</Tempo>
    <StartPoint>0</StartPoint>
    <EndPoint>0</EndPoint>
  </dtSingerHistory>
  <dtSingerHistory>
    <Count>1</Count>
    <DateTimeSang>2012-04-26T23:02:04.8947405-07:00</DateTimeSang>
    <Title>Holding Out For A Hero</Title>
    <Artist>Tyler, Bonnie</Artist>
    <DiscID />
    <Pitch>0</Pitch>
    <Path>C:\Users\Karaoke\Music\karaoke\Dec-SC\dec sc\december sc convert final-2\Tyler, Bonnie - Holding Out For A Hero.zip</Path>
    <Tempo>0</Tempo>
    <StartPoint>0</StartPoint>
    <EndPoint>0</EndPoint>
  </dtSingerHistory>
</dsSingerHistory>