<?xml version="1.0" standalone="yes"?>
<dsSingerHistory xmlns="http://tempuri.org/dsSingerHistory.xsd">
  <dtSingerHistory>
    <Count>1</Count>
    <DateTimeSang>2010-05-01T22:24:41.8051961-07:00</DateTimeSang>
    <Title>Change The World</Title>
    <Artist>Clapton, Eric</Artist>
    <DiscID />
    <Pitch>0</Pitch>
    <Path>C:\Users\Karaoke\Music\karaoke\CHB\Clapton, Eric - Change The World.zip</Path>
    <Tempo>0</Tempo>
    <StartPoint>0</StartPoint>
    <EndPoint>0</EndPoint>
  </dtSingerHistory>
  <dtSingerHistory>
    <Count>1</Count>
    <DateTimeSang>2010-05-01T23:23:08.157748-07:00</DateTimeSang>
    <Title>Lately</Title>
    <Artist>Wonder, Stevie</Artist>
    <DiscID />
    <Pitch>0</Pitch>
    <Path>C:\Users\Karaoke\Music\karaoke\sgb\Wonder, Stevie - Lately.zip</Path>
    <Tempo>0</Tempo>
    <StartPoint>0</StartPoint>
    <EndPoint>0</EndPoint>
  </dtSingerHistory>
  <dtSingerHistory>
    <Count>3</Count>
    <DateTimeSang>2011-11-13T23:58:45.6372293-08:00</DateTimeSang>
    <Title>La Bamba</Title>
    <Artist>Los Lobos</Artist>
    <DiscID />
    <Pitch>0</Pitch>
    <Path>C:\Users\Karaoke\Music\karaoke\CHB\Los Lobos - La Bamba.zip</Path>
    <Tempo>0</Tempo>
    <StartPoint>0</StartPoint>
    <EndPoint>0</EndPoint>
  </dtSingerHistory>
  <dtSingerHistory>
    <Count>1</Count>
    <DateTimeSang>2010-05-02T00:52:04.0129414-07:00</DateTimeSang>
    <Title>Don't Let The Sun Go Down On Me</Title>
    <Artist>John, Elton</Artist>
    <DiscID />
    <Pitch>0</Pitch>
    <Path>C:\Users\Karaoke\Music\karaoke\sgb toolbox\John, Elton - Don't Let The Sun Go Down On Me.zip</Path>
    <Tempo>0</Tempo>
    <StartPoint>0</StartPoint>
    <EndPoint>0</EndPoint>
  </dtSingerHistory>
  <dtSingerHistory>
    <Count>1</Count>
    <DateTimeSang>2010-05-02T01:28:03.3784501-07:00</DateTimeSang>
    <Title>Look What You've Done To Me</Title>
    <Artist>Scaggs, Boz</Artist>
    <DiscID />
    <Pitch>0</Pitch>
    <Path>C:\Users\Karaoke\Music\karaoke\SC new adds\Scaggs, Boz - Look What You've Done To Me.zip</Path>
    <Tempo>0</Tempo>
    <StartPoint>0</StartPoint>
    <EndPoint>0</EndPoint>
  </dtSingerHistory>
  <dtSingerHistory>
    <Count>1</Count>
    <DateTimeSang>2011-06-12T23:40:43.7279501-07:00</DateTimeSang>
    <Title>Boy Named Sue, A</Title>
    <Artist>Cash, Johnny</Artist>
    <DiscID />
    <Pitch>0</Pitch>
    <Path>C:\Users\Karaoke\Music\karaoke\CHB\Cash, Johnny - Boy Named Sue, A.zip</Path>
    <Tempo>0</Tempo>
    <StartPoint>0</StartPoint>
    <EndPoint>0</EndPoint>
  </dtSingerHistory>
  <dtSingerHistory>
    <Count>1</Count>
    <DateTimeSang>2011-11-14T01:33:51.5235874-08:00</DateTimeSang>
    <Title>Power Of Love, The</Title>
    <Artist>Lewis, Huey &amp; The News</Artist>
    <DiscID />
    <Pitch>0</Pitch>
    <Path>C:\Users\Karaoke\Music\karaoke\CHB\Lewis, Huey &amp; The News - Power Of Love, The.zip</Path>
    <Tempo>0</Tempo>
    <StartPoint>0</StartPoint>
    <EndPoint>0</EndPoint>
  </dtSingerHistory>
  <dtSingerHistory>
    <Count>1</Count>
    <DateTimeSang>2011-12-11T22:53:35.8794073-08:00</DateTimeSang>
    <Title>Drift Away</Title>
    <Artist>Gray, Dobie</Artist>
    <DiscID />
    <Pitch>0</Pitch>
    <Path>C:\Users\Karaoke\Music\karaoke\SC\Gray, Dobie - Drift Away.zip</Path>
    <Tempo>0</Tempo>
    <StartPoint>0</StartPoint>
    <EndPoint>0</EndPoint>
  </dtSingerHistory>
  <dtSingerHistory>
    <Count>1</Count>
    <DateTimeSang>2011-12-12T01:13:24.3281992-08:00</DateTimeSang>
    <Title>Bohemian Rhapsody</Title>
    <Artist>Queen</Artist>
    <DiscID />
    <Pitch>0</Pitch>
    <Path>C:\Users\Karaoke\Music\karaoke\2010 September\09.12\Queen - Bohemian Rhapsody.zip</Path>
    <Tempo>0</Tempo>
    <StartPoint>0</StartPoint>
    <EndPoint>0</EndPoint>
  </dtSingerHistory>
  <dtSingerHistory>
    <Count>1</Count>
    <DateTimeSang>2012-03-18T23:27:55.911152-07:00</DateTimeSang>
    <Title>Blister In The Sun</Title>
    <Artist>Violent Femmes</Artist>
    <DiscID />
    <Pitch>0</Pitch>
    <Path>C:\Users\Karaoke\Music\karaoke\SC\Violent Femmes - Blister In The Sun.zip</Path>
    <Tempo>0</Tempo>
    <StartPoint>0</StartPoint>
    <EndPoint>0</EndPoint>
  </dtSingerHistory>
  <dtSingerHistory>
    <Count>1</Count>
    <DateTimeSang>2012-03-26T00:29:42.3983737-07:00</DateTimeSang>
    <Title>Black Magic Woman</Title>
    <Artist>Santana</Artist>
    <DiscID />
    <Pitch>0</Pitch>
    <Path>C:\Users\Karaoke\Music\karaoke\CHB\Santana - Black Magic Woman.zip</Path>
    <Tempo>0</Tempo>
    <StartPoint>0</StartPoint>
    <EndPoint>0</EndPoint>
  </dtSingerHistory>
</dsSingerHistory>